cpstools/.DS_Store
cpstools/GC.py
cpstools/IR.py
cpstools/KaKs.py
cpstools/LSR_annotation.py
cpstools/Pi_combine.py
cpstools/RSCU.py
cpstools/SSRS_annotation.py
cpstools/__init__.py
cpstools/cmdline.py
cpstools/converse.py
cpstools/depth.py
cpstools/extract.py
cpstools/gbcheck.py
cpstools/ge2gb.py
cpstools/information.py
cpstools/phy_built.py
cpstools/seq_adj.py
cpstools-3.0.dist-info/LICENSE
cpstools-3.0.dist-info/METADATA
cpstools-3.0.dist-info/WHEEL
cpstools-3.0.dist-info/entry_points.txt
cpstools-3.0.dist-info/RECORD
